{
"type": "FeatureCollection",
"name": "independencia",
"crs": { "type": "name", "properties": { "name": "urn:ogc:def:crs:OGC:1.3:CRS84" } },
"features": [
{ "type": "Feature", "properties": { "id": null, "BAIRRO": "PARQUE DOS PASSAROS" }, "geometry": { "type": "Point", "coordinates": [ -46.580284079151809, -23.708017153602196 ] } },
{ "type": "Feature", "properties": { "id": null, "BAIRRO": "JARDIM STO IGNACIO" }, "geometry": { "type": "Point", "coordinates": [ -46.584347354870197, -23.705358609687924 ] } },
{ "type": "Feature", "properties": { "id": null, "BAIRRO": "JARDIM INDEPENDENCIA" }, "geometry": { "type": "Point", "coordinates": [ -46.585777113309774, -23.701813392332646 ] } },
{ "type": "Feature", "properties": { "id": null, "BAIRRO": "VILA ROSA" }, "geometry": { "type": "Point", "coordinates": [ -46.584741267909671, -23.699756290904272 ] } },
{ "type": "Feature", "properties": { "id": null, "BAIRRO": "JARDIM BRASILIA" }, "geometry": { "type": "Point", "coordinates": [ -46.581604552965707, -23.700325276405749 ] } },
{ "type": "Feature", "properties": { "id": null, "BAIRRO": "JARDIM VERA CRUZ" }, "geometry": { "type": "Point", "coordinates": [ -46.579591219652848, -23.698822571107016 ] } },
{ "type": "Feature", "properties": { "id": null, "BAIRRO": "JARDIM AURORA" }, "geometry": { "type": "Point", "coordinates": [ -46.580072668923314, -23.696984310256124 ] } },
{ "type": "Feature", "properties": { "id": null, "BAIRRO": "VILA COCA" }, "geometry": { "type": "Point", "coordinates": [ -46.580539528821944, -23.705066822251268 ] } },
{ "type": "Feature", "properties": { "id": null, "BAIRRO": "C H V ADRIANA" }, "geometry": { "type": "Point", "coordinates": [ -46.577592475711803, -23.705373199059757 ] } }
]
}
